setup.py
ngtsio/__init__.py
ngtsio/ngtsio.py
ngtsio/ngtsio_examples.py
ngtsio/test_ngtsio.py
ngtsiotest.egg-info/PKG-INFO
ngtsiotest.egg-info/SOURCES.txt
ngtsiotest.egg-info/dependency_links.txt
ngtsiotest.egg-info/top_level.txt