Metadata-Version: 1.1
Name: ngtsiotest
Version: 0.9.2
Summary: Wrapper for astropy and cfitsio readers for NGTS data files
Home-page: https://github.com/MNGuenther/ngtsio
Author: Maximilian N. Guenther
Author-email: mg719@cam.ac.uk
License: UNKNOWN
Download-URL: https://github.com/MNGuenther/ngtsio/releases
Platform: UNKNOWN
